ExcelPlugin/__init__.py
ExcelPlugin/modules/__init__.py
ExcelPlugin/modules/excel.py
ExcelPlugin/modules/multi_excel.py
ExcelPlugin/utils/__init__.py
ExcelPlugin/utils/formatter.py
ExcelPlugin/utils/funstions.py
ExcelPlugin/utils/header.py
ExcelPlugin-0.1.7.dist-info/METADATA
ExcelPlugin-0.1.7.dist-info/WHEEL
ExcelPlugin-0.1.7.dist-info/top_level.txt
ExcelPlugin-0.1.7.dist-info/RECORD
